niceadmin/__init__.py
niceadmin/admin.py
niceadmin/apps.py
niceadmin/models.py
niceadmin/urls.py
niceadmin/views.py
niceadmin/static/niceadmin/css/style.css
niceadmin/static/niceadmin/img/apple-touch-icon.png
niceadmin/static/niceadmin/img/card.jpg
niceadmin/static/niceadmin/img/favicon.png
niceadmin/static/niceadmin/img/logo.png
niceadmin/static/niceadmin/img/messages-1.jpg
niceadmin/static/niceadmin/img/messages-2.jpg
niceadmin/static/niceadmin/img/messages-3.jpg
niceadmin/static/niceadmin/img/news-1.jpg
niceadmin/static/niceadmin/img/news-2.jpg
niceadmin/static/niceadmin/img/news-3.jpg
niceadmin/static/niceadmin/img/news-4.jpg
niceadmin/static/niceadmin/img/news-5.jpg
niceadmin/static/niceadmin/img/not-found.svg
niceadmin/static/niceadmin/img/product-1.jpg
niceadmin/static/niceadmin/img/product-2.jpg
niceadmin/static/niceadmin/img/product-3.jpg
niceadmin/static/niceadmin/img/product-4.jpg
niceadmin/static/niceadmin/img/product-5.jpg
niceadmin/static/niceadmin/img/profile-img.jpg
niceadmin/static/niceadmin/img/slides-1.jpg
niceadmin/static/niceadmin/img/slides-2.jpg
niceadmin/static/niceadmin/img/slides-3.jpg
niceadmin/static/niceadmin/js/main.js
niceadmin/static/niceadmin/scss/_dashboard.scss
niceadmin/static/niceadmin/scss/_footer.scss
niceadmin/static/niceadmin/scss/_general.scss
niceadmin/static/niceadmin/scss/_header.scss
niceadmin/static/niceadmin/scss/_override.scss
niceadmin/static/niceadmin/scss/_pages.scss
niceadmin/static/niceadmin/scss/_sidebar.scss
niceadmin/static/niceadmin/scss/_variables.scss
niceadmin/static/niceadmin/scss/style.scss
niceadmin/static/niceadmin/vendor/apexcharts/apexcharts.min.js
niceadmin/static/niceadmin/vendor/apexcharts/locales/ar.json
niceadmin/static/niceadmin/vendor/apexcharts/locales/ca.json
niceadmin/static/niceadmin/vendor/apexcharts/locales/cs.json
niceadmin/static/niceadmin/vendor/apexcharts/locales/de.json
niceadmin/static/niceadmin/vendor/apexcharts/locales/el.json
django_niceadmin_ds-0.0.2.dist-info/LICENSE
django_niceadmin_ds-0.0.2.dist-info/METADATA
django_niceadmin_ds-0.0.2.dist-info/WHEEL
django_niceadmin_ds-0.0.2.dist-info/top_level.txt
django_niceadmin_ds-0.0.2.dist-info/RECORD
